tankobon/__init__.py
tankobon/__version__.py
tankobon/core.py
tankobon/documentation.md
tankobon/exceptions.py
tankobon/imposter.py
tankobon/jsonclasses.py
tankobon/models.py
tankobon/utils.py
tankobon/iso639/__init__.py
tankobon/iso639/dataset.json
tankobon/sources/__init__.py
tankobon/sources/base.py
tankobon/sources/mangadex.py
tankobon/sources/mangakakalot.py
tankobon/ui/__init__.py
tankobon/ui/__main__.py
tankobon/ui/cli.py
tankobon/ui/common.py
tankobon/ui/gui.py
tankobon/ui/resources.py
tankobon/ui/template.py
tankobon/ui/utils.py
tankobon-2022.2.1.dist-info/entry_points.txt
tankobon-2022.2.1.dist-info/LICENSE
tankobon-2022.2.1.dist-info/WHEEL
tankobon-2022.2.1.dist-info/METADATA
tankobon-2022.2.1.dist-info/RECORD
