Metadata-Version: 2.1
Name: tankobon
Version: 2022.2.1
Summary: Yet another manga downloader.
Home-page: https://github.com/ongyx/tankobon
Author: Ong Yong Xin
Author-email: ongyongxin2020+github@gmail.com
Requires-Python: >=3.6
Classifier: Programming Language :: Python :: 3
Classifier: License :: OSI Approved :: MIT License
Classifier: Operating System :: OS Independent
Requires-Dist: bbcode>=1.1.0
Requires-Dist: beautifulsoup4>=4.9.1
Requires-Dist: click>=7.1.2
Requires-Dist: coloredlogs>=14.0
Requires-Dist: filetype>=1.0.7
Requires-Dist: fpdf>=1.7.2
Requires-Dist: html5lib>=1.1
Requires-Dist: imagesize>=1.2.0
Requires-Dist: MangaDex.py>=2.0.3
Requires-Dist: natsort>=7.1.0
Requires-Dist: requests>=2.24.0
Requires-Dist: pytest ; extra == "dev"
Requires-Dist: pytest-flake8 ; extra == "dev"
Requires-Dist: pytest-mypy ; extra == "dev"
Requires-Dist: pdoc ; extra == "dev"
Requires-Dist: PySide6>=6.0.3 ; extra == "gui"
Provides-Extra: dev
Provides-Extra: gui
